QGL/BlockLabel.py
QGL/ChannelLibraries.py
QGL/Channels.py
QGL/Cliffords.py
QGL/Compiler.py
QGL/ControlFlow.py
QGL/GSTTools.py
QGL/PatternUtils.py
QGL/Plotting.py
QGL/PulsePrimitives.py
QGL/PulseSequencePlotter.py
QGL/PulseSequencer.py
QGL/PulseShapes.py
QGL/Scheduler.py
QGL/TdmInstructions.py
QGL/Tomography.py
QGL/__init__.py
QGL/config.py
QGL/config_location.py
QGL/mm.py
QGL/BasicSequences/AllXY.py
QGL/BasicSequences/BlankingSweeps.py
QGL/BasicSequences/CR.py
QGL/BasicSequences/Decoupling.py
QGL/BasicSequences/Feedback.py
QGL/BasicSequences/FlipFlop.py
QGL/BasicSequences/RB.py
QGL/BasicSequences/Rabi.py
QGL/BasicSequences/SPAM.py
QGL/BasicSequences/StarkShift.py
QGL/BasicSequences/T1T2.py
QGL/BasicSequences/__init__.py
QGL/BasicSequences/helpers.py
QGL/drivers/APS2Pattern.py
QGL/drivers/APS3Pattern.py
QGL/drivers/APSPattern.py
QGL/drivers/__init__.py
QGL-2020.1.dist-info/LICENSE
QGL-2020.1.dist-info/METADATA
QGL-2020.1.dist-info/WHEEL
QGL-2020.1.dist-info/top_level.txt
QGL-2020.1.dist-info/RECORD
