Metadata-Version: 2.1
Name: QGL
Version: 2020.1
Summary: Quantum Gate Language (QGL) is a domain specific language embedded in python for specifying pulse sequences.
Home-page: https://github.com/BBN-Q/QGL
License: Apache 2.0 License
Download-URL: https://github.com/BBN-Q/QGL
Keywords: quantum qubit experiment configuration gate language
Platform: UNKNOWN
Requires-Python: >=3.6
Requires-Dist: bbndb (>=2020.1)
Requires-Dist: numpy (>=1.11.1)
Requires-Dist: scipy (>=0.17.1)
Requires-Dist: networkx (>=1.11)
Requires-Dist: bqplot (>=0.12.2)
Requires-Dist: sqlalchemy (>=1.2.15)
